django_seeder/__init__.py
django_seeder/exceptions.py
django_seeder/guessers.py
django_seeder/models.py
django_seeder/providers.py
django_seeder/seeder.py
django_seeder/tests.py
django_seeder/management/__init__.py
django_seeder/management/commands/__init__.py
django_seeder/management/commands/seed.py
django_seeder-0.1.0.dist-info/LICENSE
django_seeder-0.1.0.dist-info/METADATA
django_seeder-0.1.0.dist-info/WHEEL
django_seeder-0.1.0.dist-info/top_level.txt
django_seeder-0.1.0.dist-info/RECORD
