Metadata-Version: 2.1
Name: django-seeder
Version: 0.1.0
Summary: Seed your Django project with fake data
Home-page: http://github.com/arnoldschan/django-seeder
Author: Arnold Samuel Chan
Author-email: arnoldsamuelc@gmail.com
License: MIT
Keywords: faker fixtures data test django seed
Platform: UNKNOWN
Classifier: Development Status :: 3 - Alpha
Classifier: Intended Audience :: Information Technology
Classifier: License :: OSI Approved :: MIT License
Classifier: Framework :: Django
Classifier: Framework :: Django :: 2.2
Classifier: Framework :: Django :: 3.2
Classifier: Framework :: Django :: 4.0
Classifier: Natural Language :: English
Classifier: Programming Language :: Python
Classifier: Programming Language :: Python :: 3
Classifier: Programming Language :: Python :: 3.6
Classifier: Programming Language :: Python :: 3.7
Classifier: Programming Language :: Python :: 3.8
Classifier: Programming Language :: Python :: 3.9
Classifier: Programming Language :: Python :: 3.10
Classifier: Topic :: Software Development :: Libraries :: Python Modules
Classifier: Topic :: Software Development :: Testing
Classifier: Topic :: Utilities
License-File: LICENSE
Requires-Dist: Faker (>=0.7.7)
Requires-Dist: django (>=1.11)
Requires-Dist: toposort (>=1.5)
